{
    "fluentMethods": true,
    "relationships": [
        {
            "relationshipName": "valorRefeicao",
            "otherEntityName": "valorRefeicao",
            "relationshipType": "many-to-one",
            "otherEntityField": "id"
        },
        {
            "relationshipName": "tipoAlimento",
            "otherEntityName": "tipoAlimento",
            "relationshipType": "many-to-many",
            "otherEntityField": "id",
            "ownerSide": true,
            "otherEntityRelationshipName": "refeicao"
        }
    ],
    "fields": [
        {
            "fieldName": "refeicao",
            "fieldType": "String",
            "fieldValidateRules": []
        }
    ],
    "changelogDate": "20171026021523",
    "dto": "no",
    "service": "no",
    "entityTableName": "refeicao",
    "jpaMetamodelFiltering": false,
    "pagination": "pager"
}
